midi_etl/__init__.py
midi_etl/arrow_upath_iomanager.py
midi_etl/constants.py
midi_etl/partitions.py
midi_etl/utils.py
midi_etl-0.0.5.dist-info/METADATA
midi_etl-0.0.5.dist-info/WHEEL
midi_etl-0.0.5.dist-info/top_level.txt
midi_etl-0.0.5.dist-info/RECORD
