Metadata-Version: 2.1
Name: midi-etl
Version: 0.0.5
Summary: Midi ETL pipelines implemented with dagster + dbt
Requires-Python: >=3.10
Requires-Dist: mido (==1.2.10)
Requires-Dist: pandas
Requires-Dist: requests
Requires-Dist: pyarrow (>=10)
Requires-Dist: dagster (==1.1.10)
Requires-Dist: s3fs
Requires-Dist: trino
Requires-Dist: dbt-core
Requires-Dist: dbt-trino
Requires-Dist: dagster-dbt
Requires-Dist: duckdb
Requires-Dist: dagstermill
Requires-Dist: jupytext
Requires-Dist: matplotlib
Requires-Dist: plotly
